pyproptest/__init__.py
pyproptest/basicGenerators.py
pyproptest/testing.py
pyproptest-0.0.2.dist-info/LICENSE
pyproptest-0.0.2.dist-info/METADATA
pyproptest-0.0.2.dist-info/WHEEL
pyproptest-0.0.2.dist-info/top_level.txt
pyproptest-0.0.2.dist-info/RECORD
