Metadata-Version: 2.1
Name: pyproptest
Version: 0.0.2
Summary: pyproptest package
Author-email: Max Whisson <whissonm9@gmail.com>
Requires-Python: >=3.7
License-File: LICENSE
